[
    {
        "key": "dbln",
        "value": "%7B%2261581493028799%22%3A%22xuWzM4jB%22%2C%2261587035134390%22%3A%22xvM2Ors2%22%7D",
        "domain": "facebook.com",
        "path": "/login/device-based/",
        "hostOnly": false,
        "creation": "2026-04-20T10:59:03.443Z",
        "lastAccessed": "2026-04-20T10:59:03.443Z"
    },
    {
        "key": "sb",
        "value": "Zd_baTAFcJyfX5fUkl0XyA4x",
        "domain": "facebook.com",
        "path": "/",
        "hostOnly": false,
        "creation": "2026-04-20T10:59:03.443Z",
        "lastAccessed": "2026-04-20T10:59:03.443Z"
    },
    {
        "key": "datr",
        "value": "rgLmadZuuPIxgWlLPFlzJo3X",
        "domain": "facebook.com",
        "path": "/",
        "hostOnly": false,
        "creation": "2026-04-20T10:59:03.443Z",
        "lastAccessed": "2026-04-20T10:59:03.443Z"
    },
    {
        "key": "m_pixel_ratio",
        "value": "2",
        "domain": "facebook.com",
        "path": "/",
        "hostOnly": false,
        "creation": "2026-04-20T10:59:03.443Z",
        "lastAccessed": "2026-04-20T10:59:03.443Z"
    },
    {
        "key": "wd",
        "value": "360x780",
        "domain": "facebook.com",
        "path": "/",
        "hostOnly": false,
        "creation": "2026-04-20T10:59:03.443Z",
        "lastAccessed": "2026-04-20T10:59:03.443Z"
    },
    {
        "key": "c_user",
        "value": "61574704469609",
        "domain": "facebook.com",
        "path": "/",
        "hostOnly": false,
        "creation": "2026-04-20T10:59:03.443Z",
        "lastAccessed": "2026-04-20T10:59:03.444Z"
    },
    {
        "key": "xs",
        "value": "33%3AFafYex_Rqiq7qA%3A2%3A1776682616%3A-1%3A-1",
        "domain": "facebook.com",
        "path": "/",
        "hostOnly": false,
        "creation": "2026-04-20T10:59:03.444Z",
        "lastAccessed": "2026-04-20T10:59:03.444Z"
    },
    {
        "key": "fr",
        "value": "0zu2U39RAcMKr31Qm.AWccPeSOv5DiIcKglIuR26EHdtRqClxKILlcpRl5bhmmPg-XN6c.Bp5gKu..AAA.0.0.Bp5gav.AWcaVPubylTrCEZP8AIjTpkNJrk",
        "domain": "facebook.com",
        "path": "/",
        "hostOnly": false,
        "creation": "2026-04-20T10:59:03.444Z",
        "lastAccessed": "2026-04-20T10:59:03.444Z"
    },
    {
        "key": "locale",
        "value": "ne_NP",
        "domain": "facebook.com",
        "path": "/",
        "hostOnly": false,
        "creation": "2026-04-20T10:59:03.444Z",
        "lastAccessed": "2026-04-20T10:59:03.444Z"
    },
    {
        "key": "pas",
        "value": "61574704469609%3AuwDMLeVC9c",
        "domain": "facebook.com",
        "path": "/",
        "hostOnly": false,
        "creation": "2026-04-20T10:59:03.444Z",
        "lastAccessed": "2026-04-20T10:59:03.444Z"
    },
    {
        "key": "wl_cbv",
        "value": "v2%3Bclient_version%3A3145%3Btimestamp%3A1776682672",
        "domain": "facebook.com",
        "path": "/",
        "hostOnly": false,
        "creation": "2026-04-20T10:59:03.444Z",
        "lastAccessed": "2026-04-20T10:59:03.444Z"
    },
    {
        "key": "fbl_st",
        "value": "100736505%3BT%3A29611378",
        "domain": "facebook.com",
        "path": "/",
        "hostOnly": false,
        "creation": "2026-04-20T10:59:03.444Z",
        "lastAccessed": "2026-04-20T10:59:03.444Z"
    },
    {
        "key": "vpd",
        "value": "v1%3B648x360x2",
        "domain": "facebook.com",
        "path": "/",
        "hostOnly": false,
        "creation": "2026-04-20T10:59:03.444Z",
        "lastAccessed": "2026-04-20T10:59:03.444Z"
    }
]
